.dolphinview
Changelog.txt
create_api_docs.sh
setup.py
ews/__init__.py
ews/battle.py
ews/char.py
ews/fight.py
ews/locale.py
ews/namen.py
ews/pmw6.py
ews.egg-info/PKG-INFO
ews.egg-info/SOURCES.txt
ews.egg-info/dependency_links.txt
ews.egg-info/top_level.txt
ews/Vorlagen/Mensch-1w6.org-2007-0.0.yml
ews/amov/Armee.py
ews/amov/Charakter.py
ews/amov/Lokalisierung.py
ews/amov/Namensgrammatik.py
ews/amov/Object.py
ews/amov/Schlacht.py
ews/amov/Versionsverwaltung.py
ews/amov/__init__.py
ews/amov/charakterverwaltung.py
ews/amov/useage_from_shell.sh
ews/amov/Charaktere/Sskreszta-draketo.de-2007-0.1.yml
ews/amov/Schlachten/Menschen_gegen_Goblins-draketo.de-2007-0.0.yml
ews/amov/Skripte/__init__.py
ews/amov/Skripte/Kernskripte/Objekt.py
ews/amov/Skripte/Kernskripte/__init__.py
ews/amov/Skripte/Kernskripte/ein_und_ausgabe/__init__.py
ews/amov/Skripte/Kernskripte/ein_und_ausgabe/tag_zu_datei.py
ews/amov/Skripte/Kernskripte/ein_und_ausgabe/tag_zu_datei_von_tag.py
ews/amov/Skripte/Kernskripte/ein_und_ausgabe/tag_zu_objekt.py
ews/amov/Spezies/Goblins-1w6.org-2007-0.1.yml
ews/amov/Spezies/Menschen-1w6.org-2007-0.1.yml
ews/amov/docs/diagrams/amov-structure-plan-diag.dot
ews/amov/docs/diagrams/amov-structure-plan-diag.png
ews/amov/docs/diagrams/current-amov-structure-diag.dot
ews/amov/docs/diagrams/current-amov-structure-diag.png
ews/namegen/__init__.py
ews/namegen/pycfnamegen/.dolphinview
ews/namegen/pycfnamegen/__init__.py
ews/namegen/pycfnamegen/cfnamegen.py
ews/random_phonetic_name_generator_von_Pointon/__init__.py
ews/random_phonetic_name_generator_von_Pointon/random_phonetic_name_generator.py
ews/yould/COPYING
ews/yould/README
ews/yould/__init__.py
ews/yould/alle_texte_von_arne.prob
ews/yould/dl-kjb.py
ews/yould/erynnia.prob
ews/yould/erynnia_und_korben.prob
ews/yould/gutenberg_erotik_und_romantik.prob
ews/yould/gutenberg_esperanto.prob
ews/yould/gutenberg_esperanto2.prob
ews/yould/kjb.prob
ews/yould/various_gutenberg.prob
ews/yould/yould-0.1.py
ews/yould/yould-train.py
ews/yould/yould.py
ews/yould/training_materials/alle_meine_texte.txt
